[
  {
    "name": "Cairo Learning Hub",
    "description": "Premier educational center in downtown Cairo offering various courses",
    "ownerId": "685b6878ad4693238cd4bfcd",
    "website": "https://cairolearninghub.edu.eg",
    "categories": "Programming",
    "contact": {
      "email": "info@cairolearninghub.edu.eg",
      "phone": "+20223456789",
      "address": "Downtown Cairo, Tahrir Square"
    },
    "socialMedia": {
      "facebook": "cairolearninghub",
      "linkedin": "company/cairolearninghub",
      "instagram": "cairolearninghub"
    },
    "isActive": true
  },
  {
    "name": "Alexandria Knowledge Center",
    "description": "Leading educational institution in Alexandria with modern facilities",
    "ownerId": "6866019e6385cdda75a0e410",
    "website": "https://alexknowledge.edu.eg",
    "categories": "Business",
    "contact": {
      "email": "contact@alexknowledge.edu.eg",
      "phone": "+2034567890",
      "address": "Roushdy, Alexandria"
    },
    "socialMedia": {
      "facebook": "alexknowledge",
      "linkedin": "company/alexknowledge",
      "instagram": "alexknowledge"
    },
    "isActive": true
  },
  {
    "name": "Giza Educational Complex",
    "description": "Comprehensive training center in Giza with multiple branches",
    "ownerId": "6866019e6385cdda75a0e410",
    "website": "https://gizaeducation.edu.eg",
    "categories": "Languages",
    "contact": {
      "email": "support@gizaeducation.edu.eg",
      "phone": "+20234567890",
      "address": "Dokki, Giza"
    },
    "socialMedia": {
      "facebook": "gizaeducation",
      "linkedin": "company/gizaeducation",
      "instagram": "gizaeducation"
    },
    "isActive": true
  }
]
